domjudge_tool_cli/__init__.py
domjudge_tool_cli/commands/__init__.py
domjudge_tool_cli/commands/emails/__init__.py
domjudge_tool_cli/commands/general/__init__.py
domjudge_tool_cli/commands/general/_check.py
domjudge_tool_cli/commands/problems/__init__.py
domjudge_tool_cli/commands/problems/_problems.py
domjudge_tool_cli/commands/scoreboard/__init__.py
domjudge_tool_cli/commands/submissions/__init__.py
domjudge_tool_cli/commands/submissions/_submissions.py
domjudge_tool_cli/commands/users/__init__.py
domjudge_tool_cli/commands/users/_users.py
domjudge_tool_cli/models/__init__.py
domjudge_tool_cli/models/affiliation.py
domjudge_tool_cli/models/domserver.py
domjudge_tool_cli/models/judgement_types.py
domjudge_tool_cli/models/judgements.py
domjudge_tool_cli/models/problem.py
domjudge_tool_cli/models/submission.py
domjudge_tool_cli/models/team.py
domjudge_tool_cli/models/user.py
domjudge_tool_cli/services/__init__.py
domjudge_tool_cli/services/api/__init__.py
domjudge_tool_cli/services/api/v4/__init__.py
domjudge_tool_cli/services/api/v4/base.py
domjudge_tool_cli/services/api/v4/general.py
domjudge_tool_cli/services/api/v4/judgement_types.py
domjudge_tool_cli/services/api/v4/judgements.py
domjudge_tool_cli/services/api/v4/problems.py
domjudge_tool_cli/services/api/v4/submissions.py
domjudge_tool_cli/services/api/v4/teams.py
domjudge_tool_cli/services/api/v4/users.py
domjudge_tool_cli/services/api_client.py
domjudge_tool_cli/services/web/__init__.py
domjudge_tool_cli/services/web/base.py
domjudge_tool_cli/services/web/v7.py
domjudge_tool_cli/services/web/v8.py
domjudge_tool_cli/templates/csv/import-users-teams.csv
domjudge_tool_cli/templates/email/body.html
domjudge_tool_cli/templates/email/body.txt
domjudge_tool_cli/templates/email/subject.txt
domjudge_tool_cli/utils/__init__.py
domjudge_tool_cli/utils/email/__init__.py
domjudge_tool_cli/utils/email/helper.py
domjudge_tool_cli/utils/email/smtp.py
domjudge_tool_cli/utils/password.py
domjudge_tool_cli-0.3.0.dist-info/METADATA
domjudge_tool_cli-0.3.0.dist-info/WHEEL
domjudge_tool_cli-0.3.0.dist-info/entry_points.txt
domjudge_tool_cli-0.3.0.dist-info/RECORD
